{
    "name":"wzry",
    "tcp":{
        "0":{
            "value":"3366000b000b4013000000",
            "offset":1,
            "packetnum":1
        },
        "1":{
            "value":"000000",
            "offset":27,
            "packetnum":1
        },
        "2":{
            "value":"3366000b000b40130",
            "offset":1,
            "packetnum":2
        },
        "3":{
            "value":"0000",
            "offset":19,
            "packetnum":2
        },
        "4":{
            "value":"000000",
            "offset":27,
            "packetnum":2
        },
        "5":{
            "value":"3366000b000b40130",
            "offset":1,
            "packetnum":3
        },
        "6":{
            "value":"0000",
            "offset":19,
            "packetnum":3
        },
        "7":{
            "value":"000000",
            "offset":27,
            "packetnum":3
        }
    },
    "udp":{
        "0":{
            "value":"010200009abcdef000011a3b",
            "offset":1,
            "packetnum":1
        },
        "1":{
            "value":"00020000",
            "offset":1,
            "packetnum":2
        },
        "2":{
            "value":"5f",
            "offset":15,
            "packetnum":2
        },
        "3":{
            "value":"010200009abcdef000011a3b",
            "offset":1,
            "packetnum":3
        }
    }
}